{
  "user": [
    {
      "id": 1,
      "fullname": "nguyenthiha",
      "username": "thiha",
      "email": "nguyenthiha@gmail.com",
      "password": "123"
    },
    {
      "fullname": "nguyen phi hien",
      "username": "PhiHien",
      "email": "phihien1011@gmail.com",
      "password": "11111",
      "id": 19
    },
    {
      "fullname": "tran doan dinh long",
      "username": "Long",
      "email": "dinhlong@gmail.com",
      "password": "1111",
      "id": 20
    },
    {
      "fullname": "le xuan tan",
      "username": "Tan",
      "email": "lexuantan@gmail.com",
      "password": "22222",
      "id": 21
    }
  ],
  "i4Customer": [
    {
      "UserName": "Rose Garden Homestay Da Nang 2",
      "Phone": "+840971010073",
      "RoomType": "deluxe",
      "numberOfPeople": "3",
      "CheckinDate": "2023-06-20",
      "CheckoutDate": "2023-06-22",
      "id": 8
    },
    {
      "UserName": "White",
      "Phone": "1241136523",
      "RoomType": "suite",
      "numberOfPeople": "3",
      "CheckinDate": "2023-06-22",
      "CheckoutDate": "2023-06-30",
      "id": 9
    }
  ]
}